foliant/backends/mkdocs.py
foliant/preprocessors/mkdocs.py
foliantcontrib.mkdocs-1.0.15.dist-info/LICENSE
foliantcontrib.mkdocs-1.0.15.dist-info/METADATA
foliantcontrib.mkdocs-1.0.15.dist-info/WHEEL
foliantcontrib.mkdocs-1.0.15.dist-info/top_level.txt
foliantcontrib.mkdocs-1.0.15.dist-info/RECORD
