Metadata-Version: 2.1
Name: foliantcontrib.mkdocs
Version: 1.0.15
Summary: MkDocs backend for Foliant documentation generator.
Home-page: https://github.com/foliant-docs/foliantcontrib.mkdocs
Author: Konstantin Molchanov
Author-email: moigagoo@live.com
License: MIT
Platform: any
Classifier: Development Status :: 5 - Production/Stable
Classifier: Environment :: Console
Classifier: Intended Audience :: Developers
Classifier: License :: OSI Approved :: MIT License
Classifier: Operating System :: OS Independent
Classifier: Programming Language :: Python
Classifier: Topic :: Documentation
Classifier: Topic :: Utilities
License-File: LICENSE
Requires-Dist: foliant (>=1.0.8)
Requires-Dist: mkdocs (>=1.3.0)
